htwrapper.py
htwrapper-1.1.4.dist-info/LICENSE.txt
htwrapper-1.1.4.dist-info/METADATA
htwrapper-1.1.4.dist-info/WHEEL
htwrapper-1.1.4.dist-info/top_level.txt
htwrapper-1.1.4.dist-info/RECORD
