Metadata-Version: 2.1
Name: htwrapper
Version: 1.1.4
Summary: HTClient Official API
Home-page: UNKNOWN
Author: HedgeTech LLC
License: UNKNOWN
Platform: UNKNOWN
Classifier: Programming Language :: Python :: 3
Classifier: License :: OSI Approved :: MIT License
Classifier: Operating System :: OS Independent
Requires-Python: >=3.6
Requires-Dist: requests (>=2.21.0)
